aprsbcn/__main__.py
aprsbcn-0.1.1.dist-info/LICENSE
aprsbcn-0.1.1.dist-info/WHEEL
aprsbcn-0.1.1.dist-info/METADATA
aprsbcn-0.1.1.dist-info/RECORD
