Metadata-Version: 2.1
Name: aprsbcn
Version: 0.1.1
Summary: 
Author: Evan Pratten
Author-email: ewpratten@gmail.com
Requires-Python: >=3.5,<4.0
Classifier: Programming Language :: Python :: 3
Classifier: Programming Language :: Python :: 3.5
Classifier: Programming Language :: Python :: 3.6
Classifier: Programming Language :: Python :: 3.7
Classifier: Programming Language :: Python :: 3.8
Classifier: Programming Language :: Python :: 3.9
Requires-Dist: aprslib (>=0.6.47,<0.7.0)
Requires-Dist: pyowm (>=3.2.0,<4.0.0)
Requires-Dist: requests (>=2.25.1,<3.0.0)
